pastaq/__init__.py
pastaq/libz.so
pastaq/libz.so.1
pastaq/libz.so.1.4.1.1
pastaq/pastaq.cpython-311-x86_64-linux-gnu.so
pastaq-0.11.3.dist-info/METADATA
pastaq-0.11.3.dist-info/WHEEL
pastaq-0.11.3.dist-info/top_level.txt
pastaq-0.11.3.dist-info/RECORD
