Metadata-Version: 2.1
Name: pastaq
Version: 0.11.3
Summary: Pipelines And Systems for Threshold Avoiding Quantification (PASTAQ): Pre-processing tools for LC-MS/MS data
Home-page: https://github.com/PASTAQ-MS/PASTAQ
Author: Alejandro Sanchez Brotons
Author-email: a.sanchez.brotons@rug.nl
Requires-Dist: pandas
Requires-Dist: seaborn
Requires-Dist: matplotlib
